tox_setuptools_version/__init__.py
tox_setuptools_version/hooks.py
tox_setuptools_version-0.0.0.3.dist-info/LICENSE
tox_setuptools_version-0.0.0.3.dist-info/METADATA
tox_setuptools_version-0.0.0.3.dist-info/WHEEL
tox_setuptools_version-0.0.0.3.dist-info/entry_points.txt
tox_setuptools_version-0.0.0.3.dist-info/top_level.txt
tox_setuptools_version-0.0.0.3.dist-info/RECORD
