Metadata-Version: 2.1
Name: tox-setuptools-version
Version: 0.0.0.3
Summary: Select SETUPTOOLS version to use with tox
Home-page: https://github.com/LvffY/tox-setuptools-version
Author: LvffY
Author-email: louberger@hotmail.fr
License: MIT
Keywords: tox,setuptools,2to3
Platform: UNKNOWN
Classifier: Development Status :: 4 - Beta
Classifier: Environment :: Console
Classifier: Framework :: tox
Classifier: Intended Audience :: Developers
Classifier: License :: OSI Approved :: MIT License
Classifier: Operating System :: OS Independent
Classifier: Programming Language :: Python :: 3.6
Classifier: Programming Language :: Python :: 3.7
Classifier: Programming Language :: Python :: 3.8
Classifier: Programming Language :: Python :: 3.9
Requires-Python: >=3.6
License-File: LICENSE
Requires-Dist: tox (>=2.0)
